README
setup.cfg
setup.py
fibra/__init__.py
fibra/event.py
fibra/msg.py
fibra/net.py
fibra/schedule.py
fibra.egg-info/PKG-INFO
fibra.egg-info/SOURCES.txt
fibra.egg-info/dependency_links.txt
fibra.egg-info/top_level.txt
fibra/handlers/__init__.py
fibra/handlers/io.py
fibra/handlers/nonblock.py
fibra/handlers/sleep.py
fibra/handlers/tasks.py
fibra/handlers/tube.py