Metadata-Version: 1.0
Name: fibra
Version: 0.0.21
Summary: Fibra provides advanced cooperative concurrency using Python generators.
Home-page: http://code.google.com/p/fibra/
Author: Mario Frasca
Author-email: mario@anche.no
License: MIT
Platform: Any
